Metadata-Version: 2.1
Name: hanabi-learning-environment
Version: 0.0.3
Summary: Learning environment for the game of hanabi.
Author: deepmind/hanabi-learning-environment
License-File: LICENSE
Requires-Dist: cffi
